odoo8_addon_l10n_ch_payment_slip_layouts-8.0.0.1.0.99.dev19-py2.7-nspkg.pth
odoo8_addon_l10n_ch_payment_slip_layouts-8.0.0.1.0.99.dev19.dist-info/DESCRIPTION.rst
odoo8_addon_l10n_ch_payment_slip_layouts-8.0.0.1.0.99.dev19.dist-info/METADATA
odoo8_addon_l10n_ch_payment_slip_layouts-8.0.0.1.0.99.dev19.dist-info/RECORD
odoo8_addon_l10n_ch_payment_slip_layouts-8.0.0.1.0.99.dev19.dist-info/WHEEL
odoo8_addon_l10n_ch_payment_slip_layouts-8.0.0.1.0.99.dev19.dist-info/metadata.json
odoo8_addon_l10n_ch_payment_slip_layouts-8.0.0.1.0.99.dev19.dist-info/namespace_packages.txt
odoo8_addon_l10n_ch_payment_slip_layouts-8.0.0.1.0.99.dev19.dist-info/top_level.txt
odoo_addons/l10n_ch_payment_slip_layouts/README.rst
odoo_addons/l10n_ch_payment_slip_layouts/__init__.py
odoo_addons/l10n_ch_payment_slip_layouts/__openerp__.py
odoo_addons/l10n_ch_payment_slip_layouts/company.py
odoo_addons/l10n_ch_payment_slip_layouts/payment_slip.py
odoo_addons/l10n_ch_payment_slip_layouts/i18n/am.po
odoo_addons/l10n_ch_payment_slip_layouts/i18n/ar.po
odoo_addons/l10n_ch_payment_slip_layouts/i18n/bg.po
odoo_addons/l10n_ch_payment_slip_layouts/i18n/bs.po
odoo_addons/l10n_ch_payment_slip_layouts/i18n/ca.po
odoo_addons/l10n_ch_payment_slip_layouts/i18n/cs.po
odoo_addons/l10n_ch_payment_slip_layouts/i18n/da.po
odoo_addons/l10n_ch_payment_slip_layouts/i18n/de.po
odoo_addons/l10n_ch_payment_slip_layouts/i18n/el_GR.po
odoo_addons/l10n_ch_payment_slip_layouts/i18n/en_GB.po
odoo_addons/l10n_ch_payment_slip_layouts/i18n/es.po
odoo_addons/l10n_ch_payment_slip_layouts/i18n/es_AR.po
odoo_addons/l10n_ch_payment_slip_layouts/i18n/es_CL.po
odoo_addons/l10n_ch_payment_slip_layouts/i18n/es_CO.po
odoo_addons/l10n_ch_payment_slip_layouts/i18n/es_CR.po
odoo_addons/l10n_ch_payment_slip_layouts/i18n/es_DO.po
odoo_addons/l10n_ch_payment_slip_layouts/i18n/es_EC.po
odoo_addons/l10n_ch_payment_slip_layouts/i18n/es_MX.po
odoo_addons/l10n_ch_payment_slip_layouts/i18n/es_PE.po
odoo_addons/l10n_ch_payment_slip_layouts/i18n/es_PY.po
odoo_addons/l10n_ch_payment_slip_layouts/i18n/es_VE.po
odoo_addons/l10n_ch_payment_slip_layouts/i18n/et.po
odoo_addons/l10n_ch_payment_slip_layouts/i18n/eu.po
odoo_addons/l10n_ch_payment_slip_layouts/i18n/fa.po
odoo_addons/l10n_ch_payment_slip_layouts/i18n/fi.po
odoo_addons/l10n_ch_payment_slip_layouts/i18n/fr.po
odoo_addons/l10n_ch_payment_slip_layouts/i18n/fr_CA.po
odoo_addons/l10n_ch_payment_slip_layouts/i18n/fr_CH.po
odoo_addons/l10n_ch_payment_slip_layouts/i18n/fr_FR.po
odoo_addons/l10n_ch_payment_slip_layouts/i18n/gl.po
