Metadata-Version: 2.0
Name: odoo8-addon-l10n-ch-payment-slip-layouts
Version: 8.0.0.1.0.99.dev19
Summary: Add new BVR/ESR payment slip layouts like invoice
Home-page: http://www.camptocamp.com
Author: Camptocamp, Odoo Community Association (OCA)
Author-email: support@odoo-community.org
License: AGPL-3
Platform: UNKNOWN
Classifier: Programming Language :: Python
Classifier: Framework :: Odoo
Classifier: License :: OSI Approved :: GNU Affero General Public License v3
Requires-Python: ~=2.7
Requires-Dist: odoo (<9.0a,>=8.0a)
Requires-Dist: odoo8-addon-l10n-ch-payment-slip
